{"yH2UFuicXmZQuXTrvgO/cw==":"ezgif-4-6a7d49bdd620.gif","/KxFITQegOdSKEDChOoA0g==":"b85cba40761169.578c9f0695ceb.gif","Lf+6QT19gNJzUnYwhO+Brg==":"xd-110x110.png","MTuxWVyJZ5t7MD9zO9HFUQ==":"1-512x512.png","Z6MhYhOQOOz2+7ko/WQ+/w==":"background2.jpg","tSWzshNK9spBhPosUnubqw==":"1-510x510.png","f+YH3n8bmgEWHcyIWm1frA==":"2-512x512.png","HWs2jqxUy/j1Q3+irP6qMA==":"3-512x512.png","rbqWpShGfVE1gWCMaZ6oiQ==":"background1.jpg","mT29N/0NvUy4WCBfmtZDYg==":"03.jpg","S6e0j8LQM41U9gE4ArgKhg==":"xd-512x512.png","VG/zQo9e1C0cm+jXgSljzg==":"background3.jpg","lI/NfEF35WvF9VFM4ARhbg==":"4-512x512.png","x3qSQy8w55tgamwNEYYwKQ==":"5-512x512.png","uIhpV88ZruCUzwVUKNBA2w==":"zzzz-1080x360.png","rHIFd1Ju4arvSM3FfNhKig==":"02.jpg","qsDObVhuh99voUACz8WCRQ==":"agate%20header-1080x360.png","mRxgXvgGSHNWAKSwU+cPqg==":"for%20you%20bro-1080x360.png","SzrorAsJnWEUeykSwFGjRg==":"hentai%20server%202-1080x360.png","r1qoVjKLrDq7Kjgu0Z+YIA==":"sayuka%203-1080x360.png","cOMNOD6HH/rVuupzl6Tm+g==":"tinker%20header-1080x360.png","PZNoOPkX9DAKUL2N3Zn7bw==":"revap%20for%20hentai%20server-1080x608.png","ljJg8s6c2N0h4ALqblaChg==":"header%20for%20hentai%20server-1080x360.png","g7lvpK04R1ggIyG4APACqQ==":"header%20for%20otaku%20server-1080x360.png","8UU5KQnd72iCRD2STTOC2g==":"1-1-512x512.png","9SAF2gkwc9YOo7PeLmRI8A==":"1312312-1468x791.png","A56noV1jVlUtdiNZmlTlkw==":"tumblr_nibss6ljq41s2t3cto1-500.gif","EMT4VoWDf0jeRkj7hYbufw==":"header%20razz-1080x360.png","GXk6oGA3xRmrMUrH8NouBw==":"header%20imark%20v2-1080x360.png","39GXhFF8n0RLXa6WpWpQNg==":"header%20aldano-1080x360.png","SPQd1xwUKTLv2JC+tT96jw==":"mio-1080x360.png","S6UiRNgnMSYlaD4usU2FNQ==":"set.png%20comp%201-322x322.png","E/PFp+uiWB8PS28NZ2emTA==":"pp%20moe%20server-482x482.png","5sfZ7XKx/dBuq/aRvBuyhg==":"tinker%20%20pp-482x482.png","L84SUe2xFswo7iVaaGVauQ==":"13-482x482.png","+TXJOMBOD+K00ZUgPGJ3aw==":"agate%20pp-482x482.png","tqTpwe8nFfMLwc6CwYNUhA==":"sam%20pp-482x482.png","yr8Mv+hTcCEwIosPZ3zx9A==":"111-482x482.png","j8zG1a3c22bLdC1qrub6iQ==":"comp%201-482x482.png","Fc1fdjx2eGBo/7fB+kkHAw==":"comp%202-482x482.png","KaD00cNxKCeEcCANA6KT5w==":"324-1080x608.png","1fIXscbftqwr195pNL0HLQ==":"mark-1080x608.png","P+b/IUeNLyxSlin1cAotRQ==":"+10-1080x360.png","AFdjZuS32sJIRBWgkgL2hw==":"xda-482x482.png","g0TZ2aIpFQUt/9sfk6d2XQ==":"xd-1080x608.png","N9/796VUj92bjN3FojA4Lg==":"sam%20header-1080x608.png","SrEtjBn5rf5bxcmbbdYuDQ==":"agate%20revamp-1080x608.png","dnzGtQzkpjmiCxtYNOq6sQ==":"sayuka%201-1080x608.png","h6Bbzq7tXurHWH2E5pAuDg==":"zzz-1080x608.png","JONvpW2yomB/GCtCPYCQ1w==":"tinker%20revamp-1080x608.png","MINjVn5st5mgtWUs1ydtfA==":"completo%20sorte-1080x608.png","clBjFmNWXBj1Vm9uxRx7Vg==":"completo-1080x608.png","Z6aVKrbITdqZO6SdwxlsLw==":"render%20aldanoo-1080x608.png","ahP6+KAWPFpSfrPOtMLHuQ==":"mio-1080x616.png","3NK/Kp2IiNo7inKFpuKOtA==":"revamp%20mark-1080x608.png","IibvKl41eruf7iZUfcqd1A==":"pp%20coffe-482x482.png","G6MyJlVJcd+R+LFzwoWSkA==":"gfuel%20desing-482x683.png","0nqeFUXSx1CcjJSq3v9wlQ==":"clase%2043-482x482.png"}